remembering_machine/__init__.py
remembering_machine-0.0.1.dist-info/licenses/LICENSE
remembering_machine-0.0.1.dist-info/METADATA
remembering_machine-0.0.1.dist-info/WHEEL
remembering_machine-0.0.1.dist-info/top_level.txt
remembering_machine-0.0.1.dist-info/RECORD
