Metadata-Version: 2.4
Name: remembering-machine
Version: 0.0.1
Summary: A Machine that remembers
Author-email: Alexander Fedotov <alex.fedotov@aol.com>
Project-URL: Homepage, https://github.com/remembering-machine/remembering-machine
Project-URL: Bug Tracker, https://github.com/remembering-machine/remembering-machinee/issues
Classifier: Programming Language :: Python :: 3
Classifier: License :: OSI Approved :: MIT License
Classifier: Operating System :: OS Independent
Requires-Python: >=3.10
License-File: LICENSE
Dynamic: license-file
